ovos_media_plugin_vlc/__init__.py
ovos_media_plugin_vlc/version.py
ovos_media_plugin_vlc-0.1.0a4.dist-info/LICENSE
ovos_media_plugin_vlc-0.1.0a4.dist-info/METADATA
ovos_media_plugin_vlc-0.1.0a4.dist-info/WHEEL
ovos_media_plugin_vlc-0.1.0a4.dist-info/entry_points.txt
ovos_media_plugin_vlc-0.1.0a4.dist-info/top_level.txt
ovos_media_plugin_vlc-0.1.0a4.dist-info/RECORD
