Metadata-Version: 2.1
Name: ovos-media-plugin-vlc
Version: 0.1.0a4
Summary: vlc plugin for ovos
Home-page: https://github.com/OpenVoiceOS/ovos-media-plugin-vlc
Author: JarbasAi
Author-email: jarbasai@mailfence.com
License: Apache-2.0
Keywords: ovos audio video OCP plugin
Platform: UNKNOWN
Requires-Dist: ovos-plugin-manager >=0.0.26a5
Requires-Dist: python-vlc >=1.1.2
